AUTHORS
INSTALL
LICENSE
MANIFEST.in
README.rst
UPGRADE
WHATSNEW
setup.py
Pyblosxom/__init__.py
Pyblosxom/_version.py
Pyblosxom/commandline.py
Pyblosxom/crashhandling.py
Pyblosxom/memcache.py
Pyblosxom/plugin_utils.py
Pyblosxom/pyblosxom.py
Pyblosxom/tools.py
Pyblosxom/cache/__init__.py
Pyblosxom/cache/base.py
Pyblosxom/cache/entrypickle.py
Pyblosxom/cache/entryshelve.py
Pyblosxom/data/blog.ini
Pyblosxom/data/config.py
Pyblosxom/data/pyblosxom.cgi
Pyblosxom/entries/__init__.py
Pyblosxom/entries/base.py
Pyblosxom/entries/fileentry.py
Pyblosxom/flavours/atom.flav/content_type
Pyblosxom/flavours/atom.flav/foot
Pyblosxom/flavours/atom.flav/head
Pyblosxom/flavours/atom.flav/story
Pyblosxom/flavours/error.flav/content_type
Pyblosxom/flavours/error.flav/foot
Pyblosxom/flavours/error.flav/head
Pyblosxom/flavours/error.flav/story
Pyblosxom/flavours/html.flav/content_type
Pyblosxom/flavours/html.flav/date_foot
Pyblosxom/flavours/html.flav/date_head
Pyblosxom/flavours/html.flav/foot
Pyblosxom/flavours/html.flav/head
Pyblosxom/flavours/html.flav/story
Pyblosxom/flavours/rss.flav/content_type
Pyblosxom/flavours/rss.flav/foot
Pyblosxom/flavours/rss.flav/head
Pyblosxom/flavours/rss.flav/story
Pyblosxom/flavours/rss20.flav/content_type
Pyblosxom/flavours/rss20.flav/foot
Pyblosxom/flavours/rss20.flav/head
Pyblosxom/flavours/rss20.flav/story
Pyblosxom/plugins/__init__.py
Pyblosxom/plugins/acronyms.py
Pyblosxom/plugins/akismetcomments.py
Pyblosxom/plugins/check_blacklist.py
Pyblosxom/plugins/check_javascript.py
Pyblosxom/plugins/check_nonhuman.py
Pyblosxom/plugins/comments.py
Pyblosxom/plugins/conditionalhttp.py
Pyblosxom/plugins/disqus.py
Pyblosxom/plugins/entrytitle.py
Pyblosxom/plugins/firstdaydiv.py
Pyblosxom/plugins/flavourfiles.py
Pyblosxom/plugins/magicword.py
Pyblosxom/plugins/markdown_parser.py
Pyblosxom/plugins/no_old_comments.py
Pyblosxom/plugins/pages.py
Pyblosxom/plugins/paginate.py
Pyblosxom/plugins/pyarchives.py
Pyblosxom/plugins/pycalendar.py
pyblosxom.egg-info/PKG-INFO
pyblosxom.egg-info/SOURCES.txt
pyblosxom.egg-info/dependency_links.txt
pyblosxom.egg-info/not-zip-safe
pyblosxom.egg-info/top_level.txt