Metadata-Version: 1.1
Name: pyblosxom
Version: 1.5.3
Summary: Pyblosxom is a file-based weblog engine.
Home-page: http://pyblosxom.github.com/
Author: Will Kahn-Greene, et al
Author-email: willg@bluesock.org
License: MIT
Keywords: blog pyblosxom cgi weblog wsgi
Platform: UNKNOWN
Classifier: Development Status :: 5 - Production/Stable
Classifier: Environment :: Web Environment
Classifier: Intended Audience :: Developers
Classifier: License :: OSI Approved :: MIT License
Classifier: Operating System :: OS Independent
Classifier: Programming Language :: Python
Classifier: Programming Language :: Python :: 2.6
Classifier: Programming Language :: Python :: 2.7
Classifier: Topic :: Internet :: WWW/HTTP
Classifier: Topic :: Internet :: WWW/HTTP :: Dynamic Content
